counhto/__init__.py
counhto/combinatorics.py
counhto/constants.py
counhto/count.py
counhto/io.py
counhto/jibes.py
counhto/jibes_core.py
counhto/jibes_data.py
counhto/main.py
counhto/marginal.py
counhto/utils.py
counhto-1.1.0.dist-info/LICENSE
counhto-1.1.0.dist-info/METADATA
counhto-1.1.0.dist-info/WHEEL
counhto-1.1.0.dist-info/entry_points.txt
counhto-1.1.0.dist-info/top_level.txt
counhto-1.1.0.dist-info/RECORD
