Metadata-Version: 2.1
Name: counhto
Version: 1.1.0
Summary: Python package for generating and demultiplexing hash tag oligo count matrices from cellranger output
Author-email: Daniel Malzl <daniel@menchelab.com>
License: MIT License
Project-URL: Homepage, https://github.com/dmalzl/counhto
Keywords: bioinformatics,single cell sequencing,sequencing,NGS,hashtag oligo counting,hashtag oligo demultiplexing,cellranger
Classifier: License :: OSI Approved :: MIT License
Classifier: Programming Language :: Python
Classifier: Programming Language :: Python :: 3
Requires-Python: >=3.10
License-File: LICENSE
Requires-Dist: pysam (>=0.20)
Requires-Dist: scipy (>=1.10)
Requires-Dist: pandas (>=1.5)
Requires-Dist: statsmodels (>=0.13)
Requires-Dist: scikit-learn (>=1.2)
Requires-Dist: numpy (>=1.23)
